unitelabs/cdk/__init__.py
unitelabs/cdk/connector.py
unitelabs/cdk/logging.py
unitelabs/cdk/main.py
unitelabs/cdk/py.typed
unitelabs/cdk/utils.py
unitelabs/cdk/cli/__init__.py
unitelabs/cdk/cli/certificate.py
unitelabs/cdk/cli/config.py
unitelabs/cdk/cli/connector.py
unitelabs/cdk/cli/dev.py
unitelabs/cdk/cli/start.py
unitelabs/cdk/cli/sync.py
unitelabs/cdk/config/__init__.py
unitelabs/cdk/config/config.py
unitelabs/cdk/config/connector_base_config.py
unitelabs/cdk/config/schema.py
unitelabs/cdk/features/__init__.py
unitelabs/cdk/features/core/__init__.py
unitelabs/cdk/features/core/authentication_service/AuthenticationService-v1_0.proto
unitelabs/cdk/features/core/authentication_service/AuthenticationService-v1_0.sila.xml
unitelabs/cdk/features/core/authentication_service/__init__.py
unitelabs/cdk/features/core/authentication_service/authentication_service.py
unitelabs/cdk/features/core/authorization_service/AuthorizationService-v1_0.proto
unitelabs/cdk/features/core/authorization_service/AuthorizationService-v1_0.sila.xml
unitelabs/cdk/features/core/authorization_service/__init__.py
unitelabs/cdk/features/core/authorization_service/authorization_service.py
unitelabs/cdk/features/core/lock_controller/LockController-v2_0.proto
unitelabs/cdk/features/core/lock_controller/LockController-v2_0.sila.xml
unitelabs/cdk/features/core/lock_controller/__init__.py
unitelabs/cdk/features/core/lock_controller/lock_controller.py
unitelabs/cdk/features/core/sila_service/SiLAService-v1_0.proto
unitelabs/cdk/features/core/sila_service/SiLAService-v1_0.sila.xml
unitelabs/cdk/features/core/sila_service/__init__.py
unitelabs/cdk/features/core/sila_service/sila_service.py
unitelabs/cdk/features/core/simulation_controller/SimulationController-v1_0.sila.xml
unitelabs/cdk/features/core/simulation_controller/__init__.py
unitelabs/cdk/features/core/simulation_controller/simulation_controller_base.py
unitelabs/cdk/features/examples/__init__.py
unitelabs_cdk-0.7.2.dist-info/METADATA
unitelabs_cdk-0.7.2.dist-info/WHEEL
unitelabs_cdk-0.7.2.dist-info/entry_points.txt
unitelabs_cdk-0.7.2.dist-info/licenses/LICENSE
unitelabs_cdk-0.7.2.dist-info/RECORD
