Metadata-Version: 2.4
Name: unitelabs-cdk
Version: 0.7.2
Summary: A framework to develop UniteLabs connectors based on the SiLA 2 standard specification.
Project-URL: homepage, https://unitelabs.io
Project-URL: repository, https://gitlab.com/unitelabs/cdk/python-cdk
Project-URL: documentation, https://docs.unitelabs.io/connector-development/overview
Project-URL: Bug Tracker, https://gitlab.com/unitelabs/cdk/python-cdk/-/issues
Author-email: UniteLabs <developers+cdk@unitelabs.io>
License-Expression: MIT
License-File: LICENSE
Keywords: SiLA 2,UniteLabs,automation,connectivity,laboratory
Classifier: Development Status :: 4 - Beta
Classifier: Intended Audience :: Developers
Classifier: Intended Audience :: Healthcare Industry
Classifier: Intended Audience :: Science/Research
Classifier: License :: OSI Approved :: MIT License
Classifier: Operating System :: OS Independent
Classifier: Programming Language :: Python :: 3 :: Only
Classifier: Programming Language :: Python :: 3.10
Classifier: Programming Language :: Python :: 3.11
Classifier: Programming Language :: Python :: 3.12
Classifier: Programming Language :: Python :: 3.13
Classifier: Programming Language :: Python :: 3.14
Classifier: Topic :: Software Development :: Libraries
Requires-Python: <4.0,>=3.10
Requires-Dist: click
Requires-Dist: deprecated
Requires-Dist: griffe
Requires-Dist: packaging
Requires-Dist: pydantic
Requires-Dist: python-dotenv
Requires-Dist: rich
Requires-Dist: ruamel-yaml
Requires-Dist: typing-extensions
Requires-Dist: unitelabs-sila~=0.6.2
Provides-Extra: dev
Requires-Dist: commitizen; extra == 'dev'
Requires-Dist: cruft; extra == 'dev'
Requires-Dist: cryptography; extra == 'dev'
Requires-Dist: pre-commit; extra == 'dev'
Requires-Dist: ruff; extra == 'dev'
Requires-Dist: watchfiles; extra == 'dev'
Provides-Extra: docs
Requires-Dist: unitelabs-jsondocs[clog]~=0.4.2; extra == 'docs'
Provides-Extra: test
Requires-Dist: pytest; extra == 'test'
Requires-Dist: pytest-asyncio; extra == 'test'
Requires-Dist: pytest-cov; extra == 'test'
